AWSTransactionalAppsStack/ArchitectureFlags.py
AWSTransactionalAppsStack/ArchitectureHelpers.py
AWSTransactionalAppsStack/ArchitectureMaker.py
AWSTransactionalAppsStack/DockerEC2.py
AWSTransactionalAppsStack/DockerEC2Standalone.py
AWSTransactionalAppsStack/__init__.py
AWSTransactionalAppsStack/build_and_push.py
AWSTransactionalAppsStack/config.py
AWSTransactionalAppsStack/uploader.py
AWSTransactionalAppsStack/Operations/Deploy.py
AWSTransactionalAppsStack/Operations/ServerSSH.py
AWSTransactionalAppsStack/Operations/__init__.py
AWSTransactionalAppsStack/iam/ec2_policy.json
AWSTransactionalAppsStack/jinja/user_data.sh
AWSTransactionalAppsStack/scripts/compose/docker-compose.yml
AWSTransactionalAppsStack/scripts/deploy/appBuild.sh
AWSTransactionalAppsStack/scripts/deploy/appDeploy.sh
AWSTransactionalAppsStack/scripts/deploy/appLoad.sh
AWSTransactionalAppsStack/scripts/deploy/appPush.sh
AWSTransactionalAppsStack/scripts/django-sample/Dockerfile
AWSTransactionalAppsStack/scripts/django-sample/docker-compose.yml
AWSTransactionalAppsStack/scripts/hello-world/Dockerfile
AWSTransactionalAppsStack/scripts/hello-world/docker-compose.yml
AWSTransactionalAppsStack/scripts/hello-world/index.html
AWSTransactionalAppsStack/scripts/loader/loader.sh
AWSTransactionalAppsStack/scripts/loader/secrets.sh
AWSTransactionalAppsStack/scripts/nginx/issue-cert.sh
AWSTransactionalAppsStack/scripts/nginx/conf.d/1.conf
AWSTransactionalAppsStack/scripts/nginx/conf.d/10-https.conf.disabled
AWSTransactionalAppsStack/scripts/nginx-local/issue-cert.sh
AWSTransactionalAppsStack/scripts/nginx-local/conf.d/1.conf
AWSTransactionalAppsStack/scripts/runonce/runonce.sh
AWSTransactionalAppsStack/scripts/runtime/bootstrap.sh
AWSTransactionalAppsStack/scripts/runtime/update.sh
AWSTransactionalAppsStack/scripts/setup/setup.sh
AWSTransactionalAppsStack/scripts/systemd/awsec2-app-update.timer
AWSTransactionalAppsStack/scripts/systemd/awsec2-app.service
awstransactionalapps-0.15.1.dist-info/METADATA
awstransactionalapps-0.15.1.dist-info/WHEEL
awstransactionalapps-0.15.1.dist-info/top_level.txt
awstransactionalapps-0.15.1.dist-info/RECORD
