Metadata-Version: 2.4
Name: AWSTransactionalApps
Version: 0.15.1
Summary: AWS Transactional Apps - A reusable Python CDKTF package for provisioning EC2-based Docker architectures with S3 script deployment
Home-page: https://www.buzzerboy.com/
Author: Buzzerboy Inc
Author-email: Buzzerboy Inc <info@buzzerboy.com>
Project-URL: Homepage, https://www.buzzerboy.com/
Project-URL: Issues, https://dev.azure.com/buzzerboyinc/buzzerboy
Classifier: Programming Language :: Python :: 3
Classifier: License :: OSI Approved :: MIT License
Classifier: Operating System :: OS Independent
Requires-Python: >=3.8
Requires-Dist: paramiko
Requires-Dist: AWSArchitectureBase
Requires-Dist: cdktf<1.0,>=0.17.0
Requires-Dist: constructs<11.0,>=10.0.0
Requires-Dist: cdktf-cdktf-provider-aws>=12.0.0
Requires-Dist: boto3>=1.26.0
Requires-Dist: botocore>=1.29.0
Requires-Dist: build
Requires-Dist: wheel
Requires-Dist: setuptools>=61.0
Dynamic: author
Dynamic: home-page
Dynamic: requires-dist
Dynamic: requires-python
